{
  "data": [
    {
      "interval": "P1",
      "enharmonic": ["d2"],
      "pieces": [
        {
          "name": "\"ABC Song\""
        },
        {
          "name": "\"Baa Baa Black Sheep\""
        },
        {
          "name": "\"Bad Guy\"",
          "composer": "Billie Eilish"
        },
        {
          "name": "\"Bohemian Rhapsody\"",
          "composer": "Queen"
        },
        {
          "name": "Danse Macabre",
          "composer": "Saint-Saëns"
        },
        {
          "name": "\"Jingle Bells\"",
          "composer": "Pierpont"
        },
        {
          "name": "The Nutcracker",
          "subtitle": "March",
          "composer": "Tchaikovsky"
        },
        {
          "name": "Piano Concerto No. 1",
          "composer": "Prokofiev"
        },
        {
          "name": "Piano Concerto No. 1",
          "movement": "I.",
          "composer": "Rachmaninoff"
        },
        {
          "name": "The Planets",
          "movement": "I.",
          "subtitle": "Mars",
          "composer": "Holst"
        },
        {
          "name": "Requiem",
          "subtitle": "Dies Irae",
          "composer": "Verdi"
        },
        {
          "name": "The Rite of Spring",
          "subtitle": "Augurs of Spring",
          "composer": "Stravinsky"
        },
        {
          "name": "The Rite of Spring",
          "subtitle": "Dance of the Earth",
          "composer": "Stravinsky"
        },
        {
          "name": "The Rite of Spring",
          "subtitle": "Dance of the Earth",
          "composer": "Stravinsky"
        },
        {
          "name": "The Rite of Spring",
          "subtitle": "Evocation of the Ancestors",
          "composer": "Stravinsky"
        },
        {
          "name": "The Rite of Spring",
          "subtitle": "Ritual Action of the Ancestors",
          "composer": "Stravinsky"
        },
        {
          "name": "The Rite of Spring",
          "subtitle": "Sacrificial Dance",
          "composer": "Stravinsky"
        },
        {
          "name": "Serenade No. 13 \"Eine kleine Nachtmusik\"",
          "movement": "II.",
          "composer": "Mozart"
        },
        {
          "name": "\"Sleigh Ride\"",
          "composer": "Anderson",
          "note": "main theme"
        },
        {
          "name": "Symphonie fantastique",
          "movement": "I.",
          "composer": "Berlioz"
        },
        {
          "name": "Symphony No. 2",
          "movement": "I.",
          "composer": "Sibelius"
        },
        {
          "name": "Symphony No. 2",
          "movement": "III.",
          "composer": "Sibelius"
        },
        {
          "name": "Symphony No. 2",
          "movement": "I.",
          "composer": "Prokofiev"
        },
        {
          "name": "Symphony No. 3",
          "movement": "I.",
          "composer": "Sibelius"
        },
        {
          "name": "Symphony No. 3",
          "movement": "III.",
          "composer": "Sibelius",
          "note": "chorale theme at rehearsal 12 following the scherzo"
        },
        {
          "name": "Symphony No. 4 \"Italian\"",
          "movement": "I.",
          "composer": "Mendelssohn"
        },
        {
          "name": "Symphony No. 4",
          "movement": "I.",
          "composer": "Tchaikovsky"
        },
        {
          "name": "Symphony No. 5",
          "movement": "I.",
          "composer": "Beethoven"
        },
        {
          "name": "Symphony No. 5 \"Reformation\"",
          "movement": "I.",
          "composer": "Mendelssohn",
          "note": "Allegro con fuoco"
        },
        {
          "name": "Symphony No. 5 \"Reformation\"",
          "movement": "II.",
          "composer": "Mendelssohn"
        },
        {
          "name": "Symphony No. 5 \"Reformation\"",
          "movement": "III.",
          "composer": "Mendelssohn"
        },
        {
          "name": "Tzigane",
          "composer": "Ravel"
        },
        {
          "name": "Violin Concerto",
          "movement": "III.",
          "composer": "Sibelius"
        },
        {
          "name": "Warsaw Concerto",
          "composer": "Addinsell"
        },
        {
          "name": "West Side Story",
          "subtitle": "Maria",
          "composer": "Bernstein",
          "note": "voice"
        }
      ],
      "gridRow": 1
    },
    {
      "interval": "m2",
      "enharmonic": ["A1"],
      "pieces": [
        {
          "name": "Bagatelle No. 25",
          "subtitle": "Für Elise",
          "composer": "Beethoven",
          "motion": "ad"
        },
        {
          "name": "\"The Box\"",
          "composer": "Moore",
          "motion": "d"
        },
        {
          "name": "\"Merry-Go-Round of Life\"",
          "composer": "Hisaishi",
          "motion": "ad"
        },
        {
          "name": "The Nutcracker",
          "subtitle": "Pas de Deux",
          "composer": "Tchaikovsky",
          "motion": "d"
        },
        {
          "name": "Symphony No. 1",
          "movement": "I.",
          "composer": "Sibelius",
          "motion": "ad"
        },
        {
          "name": "Symphony No. 2",
          "movement": "I.",
          "composer": "Rachmaninoff",
          "motion": "ad"
        },
        {
          "name": "Symphony No. 3 \"The Fiery Angel\"",
          "movement": "I.",
          "composer": "Prokofiev",
          "motion": "ad"
        },
        {
          "name": "Symphony No. 9 \"New World Symphony\"",
          "movement": "IV.",
          "composer": "Dvorak"
        },
        {
          "name": "\"Theme from 'Jaws'\"",
          "composer": "Williams"
        },
        {
          "name": "Violin Concerto",
          "movement": "III.",
          "composer": "Sibelius",
          "note": "solo violin"
        },
        {
          "name": "Violin Concerto",
          "movement": "I.",
          "composer": "Tchaikovsky",
          "note": "solo violin"
        },
        {
          "name": "\"Viva la Vida\"",
          "composer": "Coldplay"
        }
      ],
      "gridRow": 2
    },
    {
      "interval": "M2",
      "enharmonic": ["d3"],
      "pieces": [
        {
          "name": "\"Happy Birthday\""
        },
        {
          "name": "The Nutcracker",
          "subtitle": "Coffee",
          "composer": "Tchaikovsky",
          "motion": "ad"
        },
        {
          "name": "Piano Concerto No. 2",
          "movement": "I.",
          "composer": "Rachmaninoff",
          "motion": "ad",
          "note": "solo piano"
        },
        {
          "name": "Symphony No. 2",
          "movement": "IV.",
          "composer": "Sibelius"
        },
        {
          "name": "Symphony No. 5",
          "movement": "I.",
          "composer": "Prokofiev"
        },
        {
          "name": "Symphony No. 7",
          "composer": "Sibelius"
        },
        {
          "name": "Waltz No. 9",
          "composer": "Tchaikovsky",
          "motion": "ad"
        }
      ],
      "gridRow": 2
    },
    {
      "interval": "m3",
      "enharmonic": ["A2"],
      "pieces": [
        {
          "name": "\"Hedwig's Theme\"",
          "composer": "Williams",
          "note": "skipping the anacrusis"
        },
        {
          "name": "Miroirs",
          "movement": "III.",
          "subtitle": "Une barque sur l'océan",
          "composer": "Ravel",
          "motion": "d"
        },
        {
          "name": "The Nutcracker",
          "subtitle": "Dance of the Sugar Plum Fairy",
          "composer": "Tchaikovsky",
          "motion": "ad"
        },
        {
          "name": "Piano Concerto No. 3",
          "movement": "I.",
          "composer": "Beethoven"
        },
        {
          "name": "Piano Concerto No. 3",
          "movement": "I.",
          "composer": "Rachmaninoff",
          "note": "solo piano"
        },
        {
          "name": "Symphony No. 5",
          "movement": "II.",
          "composer": "Prokofiev",
          "motion": "ad"
        },
        {
          "name": "Symphony No. 9 \"New World Symphony\"",
          "movement": "II.",
          "composer": "Dvorak",
          "note": "English horn"
        },
        {
          "name": "Violin Concerto No. 2",
          "movement": "I.",
          "composer": "Prokofiev"
        }
      ],
      "gridRow": 3
    },
    {
      "interval": "M3",
      "enharmonic": ["d4"],
      "pieces": [
        {
          "name": "The Four Seasons Concerto No. 1 \"Spring\"",
          "movement": "I.",
          "composer": "Vivaldi"
        },
        {
          "name": "Symphony No. 4 \"Italian\"",
          "movement": "I.",
          "composer": "Mendelssohn",
          "note": "violins"
        },
        {
          "name": "Symphony No. 4 \"The Prodigal Son\"",
          "movement": "I.",
          "composer": "Prokofiev",
          "note": "flute, oboe, bassoon"
        },
        {
          "name": "Symphony No. 5",
          "movement": "I.",
          "composer": "Beethoven",
          "motion": "d"
        },
        {
          "name": "Symphony No. 5",
          "movement": "IV.",
          "composer": "Beethoven"
        },
        {
          "name": "\"Take on Me\"",
          "composer": "a-ha",
          "motion": "d",
          "note": "beginning instrumental"
        }
      ],
      "gridRow": 3
    },
    {
      "interval": "P4",
      "enharmonic": ["A3"],
      "pieces": [
        {
          "name": "\"Amazing Grace\"",
          "composer": "Newton"
        },
        {
          "name": "Fanfare for the Common Man",
          "composer": "Copland"
        },
        {
          "name": "\"Hedwig's Theme\"",
          "composer": "Williams"
        },
        {
          "name": "\"The Magic School Bus\"",
          "composer": "Lurye"
        },
        {
          "name": "\"Merry-Go-Round of Life\"",
          "composer": "Hisaishi",
          "motion": "ad",
          "note": "main theme"
        },
        {
          "name": "The Nutcracker",
          "subtitle": "Waltz of the Flowers",
          "composer": "Tchaikovsky"
        },
        {
          "name": "Serenade No. 13 \"Eine kleine Nachtmusik\"",
          "movement": "I.",
          "composer": "Mozart",
          "motion": "ad"
        },
        {
          "name": "Symphony No. 5",
          "movement": "I.",
          "composer": "Sibelius"
        },
        {
          "name": "Symphony No. 9 \"New World Symphony\"",
          "movement": "III.",
          "composer": "Dvorak",
          "note": "strings",
          "motion": "d"
        },
        {
          "name": "Violin Concerto No. 1",
          "movement": "I.",
          "composer": "Prokofiev"
        }
      ],
      "gridRow": 4
    },
    {
      "interval": "TT",
      "enharmonic": ["A4", "d5"],
      "pieces": [
        {
          "name": "Danse Macabre",
          "composer": "Saint-Saëns",
          "motion": "adh",
          "note": "solo violin"
        },
        {
          "name": "West Side Story",
          "subtitle": "Cool",
          "composer": "Bernstein",
          "motion": "ad"
        },
        {
          "name": "West Side Story",
          "subtitle": "Maria",
          "composer": "Bernstein",
          "note": "main theme"
        }
      ],
      "gridRow": 5,
      "gridColumn": 2
    },
    {
      "interval": "P5",
      "enharmonic": ["d6"],
      "pieces": [
        {
          "name": "Forest Gump Suite",
          "composer": "Silvestri"
        },
        {
          "name": "The Planets",
          "movement": "I.",
          "subtitle": "Mars",
          "composer": "Holst",
          "note": "bassoon, horn"
        }
      ],
      "gridRow": 6
    },
    {
      "interval": "m6",
      "enharmonic": ["A5"],
      "pieces": [
        {
          "name": "Requiem",
          "subtitle": "Lacrimosa",
          "composer": "Mozart",
          "note": "soprano"
        },
        {
          "name": "Symphony No. 5",
          "movement": "I.",
          "composer": "Shostakovich",
          "motion": "ad"
        }
      ],
      "gridRow": 7
    },
    {
      "interval": "M6",
      "enharmonic": ["d7"],
      "pieces": [
        {
          "name": "Nocturne No. 2",
          "composer": "Chopin"
        }
      ],
      "gridRow": 7
    },
    {
      "interval": "m7",
      "enharmonic": ["A6"],
      "pieces": [
        {
          "name": "Piano Concerto No. 4",
          "movement": "I.",
          "composer": "Rachmaninoff",
          "motion": "ad",
          "note": "melodic line between the piano and orchestra at the top of the phrase at rehearsal 29"
        },
        {
          "name": "West Side Story",
          "subtitle": "Somewhere",
          "composer": "Bernstein"
        }
      ],
      "gridRow": 8
    },
    {
      "interval": "M7",
      "enharmonic": ["d8"],
      "pieces": [
        {
          "name": "Pictures at an Exhibition",
          "movement": "9.",
          "subtitle": "The Hut on Hen's Legs (Baba Yaga)",
          "composer": "Mussorgsky",
          "motion": "d"
        },
        {
          "name": "\"Take on Me\"",
          "composer": "a-ha",
          "note": "first chorus"
        }
      ],
      "gridRow": 8
    },
    {
      "interval": "P8",
      "enharmonic": ["A7"],
      "pieces": [
        {
          "name": "The Four Seasons Concerto No. 1 \"Summer\"",
          "movement": "III.",
          "composer": "Vivaldi",
          "motion": "d"
        },
        {
          "name": "Musica Ricerata",
          "movement": "I.",
          "composer": "Ligeti",
          "motion": "adh"
        },
        {
          "name": "\"Over the Rainbow\"",
          "composer": "Arlen"
        },
        {
          "name": "Suite bergamasque",
          "movement": "III.",
          "subtitle": "Clair de Lune",
          "composer": "Debussy"
        },
        {
          "name": "Warsaw Concerto",
          "composer": "Addinsell"
        }
      ],
      "gridRow": 9
    }
  ]
}
